AUTHORS
LICENSE
MANIFEST.in
README.rst
requirements.txt
setup.py
version.py
alignak_module_logs/__init__.py
alignak_module_logs/__init__.pyc
alignak_module_logs/logevent.py
alignak_module_logs/logevent.pyc
alignak_module_logs/logs.py
alignak_module_logs/logs.pyc
alignak_module_logs.egg-info/PKG-INFO
alignak_module_logs.egg-info/SOURCES.txt
alignak_module_logs.egg-info/dependency_links.txt
alignak_module_logs.egg-info/not-zip-safe
alignak_module_logs.egg-info/requires.txt
alignak_module_logs.egg-info/top_level.txt
alignak_module_logs/etc/__init__.py
alignak_module_logs/etc/arbiter/modules/mod-logs-logger.json
alignak_module_logs/etc/arbiter/modules/mod-logs.cfg
test/test_module.py
test/test_module_backend.py
test/test_parse_logevent.py